codec/diameter/__init__.py
codec/diameter/_avp_decoder.py
codec/diameter/_avp_encoder.py
codec/diameter/_diam_tools.py
codec/diameter/diameter.py
codec/diameter/dictionary.py
diameter_codec-1.0.3.dist-info/METADATA
diameter_codec-1.0.3.dist-info/WHEEL
diameter_codec-1.0.3.dist-info/namespace_packages.txt
diameter_codec-1.0.3.dist-info/top_level.txt
diameter_codec-1.0.3.dist-info/zip-safe
diameter_codec-1.0.3.dist-info/RECORD
