Metadata-Version: 2.1
Name: diameter-codec
Version: 1.0.3
Home-page: https://gitlab.com/3gpp-toolbox/diameter-codec
Author: Kresimir Popovic
Author-email: kresimir.popovic@gmail.com
Maintainer: 
Maintainer-email: 
License: European Union Public Licence 1.2 (EUPL 1.2)
Keywords: diameter codec rfc6733
Classifier: Development Status :: 4 - Beta
Classifier: Environment :: Console
Classifier: Intended Audience :: Developers
Classifier: License :: OSI Approved :: European Union Public Licence 1.2 (EUPL 1.2)
Classifier: Operating System :: OS Independent
Classifier: Programming Language :: Python :: 3.6
Classifier: Programming Language :: Python :: 3.7
Classifier: Programming Language :: Python :: 3.8
Classifier: Programming Language :: Python :: 3.9
Classifier: Programming Language :: Python :: 3.10
Classifier: Programming Language :: Python :: 3.11
Requires-Python: >=3.6
